Metadata-Version: 2.4
Name: scxt
Version: 0.1.5
Summary: Superchain exchange trading library
License: MIT
Requires-Python: >=3.12
License-File: LICENSE
Requires-Dist: pydantic>=2.10.6
Requires-Dist: web3>=7.9.0
Dynamic: license-file
